artifactory_du/__init__.py
artifactory_du/__main__.py
artifactory_du/artifactory_du.py
artifactory_du/du.py
artifactory_du/requirements.txt
artifactory_du/version.py
artifactory_du-1.0.5.dist-info/LICENSE
artifactory_du-1.0.5.dist-info/METADATA
artifactory_du-1.0.5.dist-info/WHEEL
artifactory_du-1.0.5.dist-info/entry_points.txt
artifactory_du-1.0.5.dist-info/top_level.txt
artifactory_du-1.0.5.dist-info/RECORD
