Metadata-Version: 2.1
Name: artifactory-du
Version: 1.0.5
Summary: Artifactory Disk Usage command line interface (artifactory-du)
Home-page: https://devopshq.github.io/artifactory-du
Author: DevOpsHQ
Author-email: allburov@gmail.com
License: MIT
Keywords: disk,usage,artifactory,jfrog,devopshq
Platform: UNKNOWN
Classifier: Development Status :: 5 - Production/Stable
Classifier: Intended Audience :: Developers
Classifier: Topic :: Software Development :: Build Tools
Classifier: License :: OSI Approved :: MIT License
Classifier: Programming Language :: Python :: 3
Classifier: Programming Language :: Python :: 3.4
Classifier: Programming Language :: Python :: 3.5
Classifier: Programming Language :: Python :: 3.6
Requires-Dist: requests
Requires-Dist: requests-kerberos
Requires-Dist: dohq-artifactory
Requires-Dist: hurry.filesize
Requires-Dist: setuptools (>=46.1) ; python_version >= "3.6"
Requires-Dist: setuptools-rust ; python_version >= "3.6"
